telegram_markdown/__init__.py
telegram_markdown/parser.py
telegram_markdown_entities-0.1.1.dist-info/licenses/LICENSE
telegram_markdown_entities-0.1.1.dist-info/METADATA
telegram_markdown_entities-0.1.1.dist-info/WHEEL
telegram_markdown_entities-0.1.1.dist-info/top_level.txt
telegram_markdown_entities-0.1.1.dist-info/RECORD
