Metadata-Version: 2.4
Name: telegram-markdown-entities
Version: 0.1.1
Summary: Convert Markdown into plain text and Telegram message entities.
Author-email: Lebedev Nikolay <fifo.mail@gmail.com>
License: MIT
Project-URL: Source, https://github.com/bakaut/telegram-markdown-entities
Project-URL: Issues, https://github.com/bakaut/telegram-markdown-entities/issues
Keywords: telegram,markdown,entities,bot,tg
Classifier: Programming Language :: Python :: 3
Classifier: Programming Language :: Python :: 3 :: Only
Classifier: License :: OSI Approved :: MIT License
Classifier: Operating System :: OS Independent
Requires-Python: >=3.7
License-File: LICENSE
Dynamic: license-file
